[
  {
    "ContainingType": "personapi_dotnet.Controllers.EstudiosController",
    "Method": "GetAll",
    "RelativePath": "api/Estudios",
    "HttpMethod": "GET",
    "IsController": true,
    "Order": 0,
    "Parameters": [],
    "ReturnTypes": [
      {
        "Type": "System.Collections.Generic.IEnumerable\u00601[[personapi_dotnet.Models.Entities.Estudio, personapi-dotnet, Version=1.0.0.0, Culture=neutral, PublicKeyToken=null]]",
        "MediaTypes": [
          "text/plain",
          "application/json",
          "text/json"
        ],
        "StatusCode": 200
      }
    ]
  },
  {
    "ContainingType": "personapi_dotnet.Controllers.EstudiosController",
    "Method": "Create",
    "RelativePath": "api/Estudios",
    "HttpMethod": "POST",
    "IsController": true,
    "Order": 0,
    "Parameters": [
      {
        "Name": "estudio",
        "Type": "personapi_dotnet.Models.Entities.Estudio",
        "IsRequired": true
      }
    ],
    "ReturnTypes": [
      {
        "Type": "personapi_dotnet.Models.Entities.Estudio",
        "MediaTypes": [
          "text/plain",
          "application/json",
          "text/json"
        ],
        "StatusCode": 200
      }
    ]
  },
  {
    "ContainingType": "personapi_dotnet.Controllers.EstudiosController",
    "Method": "Update",
    "RelativePath": "api/Estudios",
    "HttpMethod": "PUT",
    "IsController": true,
    "Order": 0,
    "Parameters": [
      {
        "Name": "estudio",
        "Type": "personapi_dotnet.Models.Entities.Estudio",
        "IsRequired": true
      }
    ],
    "ReturnTypes": []
  },
  {
    "ContainingType": "personapi_dotnet.Controllers.EstudiosController",
    "Method": "Delete",
    "RelativePath": "api/Estudios/{idProf}/{ccPer}",
    "HttpMethod": "DELETE",
    "IsController": true,
    "Order": 0,
    "Parameters": [
      {
        "Name": "idProf",
        "Type": "System.Int32",
        "IsRequired": true
      },
      {
        "Name": "ccPer",
        "Type": "System.Int32",
        "IsRequired": true
      }
    ],
    "ReturnTypes": []
  },
  {
    "ContainingType": "personapi_dotnet.Controllers.EstudiosController",
    "Method": "GetByPersona",
    "RelativePath": "api/Estudios/persona/{ccPersona}",
    "HttpMethod": "GET",
    "IsController": true,
    "Order": 0,
    "Parameters": [
      {
        "Name": "ccPersona",
        "Type": "System.Int32",
        "IsRequired": true
      }
    ],
    "ReturnTypes": [
      {
        "Type": "System.Collections.Generic.IEnumerable\u00601[[personapi_dotnet.Models.Entities.Estudio, personapi-dotnet, Version=1.0.0.0, Culture=neutral, PublicKeyToken=null]]",
        "MediaTypes": [
          "text/plain",
          "application/json",
          "text/json"
        ],
        "StatusCode": 200
      }
    ]
  },
  {
    "ContainingType": "personapi_dotnet.Controllers.EstudiosController",
    "Method": "GetByProfesion",
    "RelativePath": "api/Estudios/profesion/{idProfesion}",
    "HttpMethod": "GET",
    "IsController": true,
    "Order": 0,
    "Parameters": [
      {
        "Name": "idProfesion",
        "Type": "System.Int32",
        "IsRequired": true
      }
    ],
    "ReturnTypes": [
      {
        "Type": "System.Collections.Generic.IEnumerable\u00601[[personapi_dotnet.Models.Entities.Estudio, personapi-dotnet, Version=1.0.0.0, Culture=neutral, PublicKeyToken=null]]",
        "MediaTypes": [
          "text/plain",
          "application/json",
          "text/json"
        ],
        "StatusCode": 200
      }
    ]
  },
  {
    "ContainingType": "personapi_dotnet.Controllers.PersonasController",
    "Method": "GetAll",
    "RelativePath": "api/Personas",
    "HttpMethod": "GET",
    "IsController": true,
    "Order": 0,
    "Parameters": [],
    "ReturnTypes": [
      {
        "Type": "System.Collections.Generic.IEnumerable\u00601[[personapi_dotnet.Models.Entities.Persona, personapi-dotnet, Version=1.0.0.0, Culture=neutral, PublicKeyToken=null]]",
        "MediaTypes": [
          "text/plain",
          "application/json",
          "text/json"
        ],
        "StatusCode": 200
      }
    ]
  },
  {
    "ContainingType": "personapi_dotnet.Controllers.PersonasController",
    "Method": "Create",
    "RelativePath": "api/Personas",
    "HttpMethod": "POST",
    "IsController": true,
    "Order": 0,
    "Parameters": [
      {
        "Name": "persona",
        "Type": "personapi_dotnet.Models.Entities.Persona",
        "IsRequired": true
      }
    ],
    "ReturnTypes": [
      {
        "Type": "personapi_dotnet.Models.Entities.Persona",
        "MediaTypes": [
          "text/plain",
          "application/json",
          "text/json"
        ],
        "StatusCode": 200
      }
    ]
  },
  {
    "ContainingType": "personapi_dotnet.Controllers.PersonasController",
    "Method": "GetByCc",
    "RelativePath": "api/Personas/{cc}",
    "HttpMethod": "GET",
    "IsController": true,
    "Order": 0,
    "Parameters": [
      {
        "Name": "cc",
        "Type": "System.Int32",
        "IsRequired": true
      }
    ],
    "ReturnTypes": [
      {
        "Type": "personapi_dotnet.Models.Entities.Persona",
        "MediaTypes": [
          "text/plain",
          "application/json",
          "text/json"
        ],
        "StatusCode": 200
      }
    ]
  },
  {
    "ContainingType": "personapi_dotnet.Controllers.PersonasController",
    "Method": "Update",
    "RelativePath": "api/Personas/{cc}",
    "HttpMethod": "PUT",
    "IsController": true,
    "Order": 0,
    "Parameters": [
      {
        "Name": "cc",
        "Type": "System.Int32",
        "IsRequired": true
      },
      {
        "Name": "persona",
        "Type": "personapi_dotnet.Models.Entities.Persona",
        "IsRequired": true
      }
    ],
    "ReturnTypes": []
  },
  {
    "ContainingType": "personapi_dotnet.Controllers.PersonasController",
    "Method": "Delete",
    "RelativePath": "api/Personas/{cc}",
    "HttpMethod": "DELETE",
    "IsController": true,
    "Order": 0,
    "Parameters": [
      {
        "Name": "cc",
        "Type": "System.Int32",
        "IsRequired": true
      }
    ],
    "ReturnTypes": []
  },
  {
    "ContainingType": "personapi_dotnet.Controllers.PersonasController",
    "Method": "GetByEdad",
    "RelativePath": "api/Personas/edad/{edad}",
    "HttpMethod": "GET",
    "IsController": true,
    "Order": 0,
    "Parameters": [
      {
        "Name": "edad",
        "Type": "System.Int32",
        "IsRequired": true
      }
    ],
    "ReturnTypes": [
      {
        "Type": "System.Collections.Generic.IEnumerable\u00601[[personapi_dotnet.Models.Entities.Persona, personapi-dotnet, Version=1.0.0.0, Culture=neutral, PublicKeyToken=null]]",
        "MediaTypes": [
          "text/plain",
          "application/json",
          "text/json"
        ],
        "StatusCode": 200
      }
    ]
  },
  {
    "ContainingType": "personapi_dotnet.Controllers.PersonasController",
    "Method": "GetByGenero",
    "RelativePath": "api/Personas/genero/{genero}",
    "HttpMethod": "GET",
    "IsController": true,
    "Order": 0,
    "Parameters": [
      {
        "Name": "genero",
        "Type": "System.String",
        "IsRequired": true
      }
    ],
    "ReturnTypes": [
      {
        "Type": "System.Collections.Generic.IEnumerable\u00601[[personapi_dotnet.Models.Entities.Persona, personapi-dotnet, Version=1.0.0.0, Culture=neutral, PublicKeyToken=null]]",
        "MediaTypes": [
          "text/plain",
          "application/json",
          "text/json"
        ],
        "StatusCode": 200
      }
    ]
  },
  {
    "ContainingType": "personapi_dotnet.Controllers.ProfesionesController",
    "Method": "GetAll",
    "RelativePath": "api/Profesiones",
    "HttpMethod": "GET",
    "IsController": true,
    "Order": 0,
    "Parameters": [],
    "ReturnTypes": [
      {
        "Type": "System.Collections.Generic.IEnumerable\u00601[[personapi_dotnet.Models.Entities.Profesion, personapi-dotnet, Version=1.0.0.0, Culture=neutral, PublicKeyToken=null]]",
        "MediaTypes": [
          "text/plain",
          "application/json",
          "text/json"
        ],
        "StatusCode": 200
      }
    ]
  },
  {
    "ContainingType": "personapi_dotnet.Controllers.ProfesionesController",
    "Method": "Create",
    "RelativePath": "api/Profesiones",
    "HttpMethod": "POST",
    "IsController": true,
    "Order": 0,
    "Parameters": [
      {
        "Name": "profesion",
        "Type": "personapi_dotnet.Models.Entities.Profesion",
        "IsRequired": true
      }
    ],
    "ReturnTypes": [
      {
        "Type": "personapi_dotnet.Models.Entities.Profesion",
        "MediaTypes": [
          "text/plain",
          "application/json",
          "text/json"
        ],
        "StatusCode": 200
      }
    ]
  },
  {
    "ContainingType": "personapi_dotnet.Controllers.ProfesionesController",
    "Method": "GetById",
    "RelativePath": "api/Profesiones/{id}",
    "HttpMethod": "GET",
    "IsController": true,
    "Order": 0,
    "Parameters": [
      {
        "Name": "id",
        "Type": "System.Int32",
        "IsRequired": true
      }
    ],
    "ReturnTypes": [
      {
        "Type": "personapi_dotnet.Models.Entities.Profesion",
        "MediaTypes": [
          "text/plain",
          "application/json",
          "text/json"
        ],
        "StatusCode": 200
      }
    ]
  },
  {
    "ContainingType": "personapi_dotnet.Controllers.ProfesionesController",
    "Method": "Update",
    "RelativePath": "api/Profesiones/{id}",
    "HttpMethod": "PUT",
    "IsController": true,
    "Order": 0,
    "Parameters": [
      {
        "Name": "id",
        "Type": "System.Int32",
        "IsRequired": true
      },
      {
        "Name": "profesion",
        "Type": "personapi_dotnet.Models.Entities.Profesion",
        "IsRequired": true
      }
    ],
    "ReturnTypes": []
  },
  {
    "ContainingType": "personapi_dotnet.Controllers.ProfesionesController",
    "Method": "Delete",
    "RelativePath": "api/Profesiones/{id}",
    "HttpMethod": "DELETE",
    "IsController": true,
    "Order": 0,
    "Parameters": [
      {
        "Name": "id",
        "Type": "System.Int32",
        "IsRequired": true
      }
    ],
    "ReturnTypes": []
  },
  {
    "ContainingType": "personapi_dotnet.Controllers.ProfesionesController",
    "Method": "GetByNombre",
    "RelativePath": "api/Profesiones/buscar/{nombre}",
    "HttpMethod": "GET",
    "IsController": true,
    "Order": 0,
    "Parameters": [
      {
        "Name": "nombre",
        "Type": "System.String",
        "IsRequired": true
      }
    ],
    "ReturnTypes": [
      {
        "Type": "System.Collections.Generic.IEnumerable\u00601[[personapi_dotnet.Models.Entities.Profesion, personapi-dotnet, Version=1.0.0.0, Culture=neutral, PublicKeyToken=null]]",
        "MediaTypes": [
          "text/plain",
          "application/json",
          "text/json"
        ],
        "StatusCode": 200
      }
    ]
  },
  {
    "ContainingType": "personapi_dotnet.Controllers.TelefonosController",
    "Method": "GetAll",
    "RelativePath": "api/Telefonos",
    "HttpMethod": "GET",
    "IsController": true,
    "Order": 0,
    "Parameters": [],
    "ReturnTypes": [
      {
        "Type": "System.Collections.Generic.IEnumerable\u00601[[personapi_dotnet.Models.Entities.Telefono, personapi-dotnet, Version=1.0.0.0, Culture=neutral, PublicKeyToken=null]]",
        "MediaTypes": [
          "text/plain",
          "application/json",
          "text/json"
        ],
        "StatusCode": 200
      }
    ]
  },
  {
    "ContainingType": "personapi_dotnet.Controllers.TelefonosController",
    "Method": "Create",
    "RelativePath": "api/Telefonos",
    "HttpMethod": "POST",
    "IsController": true,
    "Order": 0,
    "Parameters": [
      {
        "Name": "telefono",
        "Type": "personapi_dotnet.Models.Entities.Telefono",
        "IsRequired": true
      }
    ],
    "ReturnTypes": [
      {
        "Type": "personapi_dotnet.Models.Entities.Telefono",
        "MediaTypes": [
          "text/plain",
          "application/json",
          "text/json"
        ],
        "StatusCode": 200
      }
    ]
  },
  {
    "ContainingType": "personapi_dotnet.Controllers.TelefonosController",
    "Method": "GetByNumero",
    "RelativePath": "api/Telefonos/{numero}",
    "HttpMethod": "GET",
    "IsController": true,
    "Order": 0,
    "Parameters": [
      {
        "Name": "numero",
        "Type": "System.String",
        "IsRequired": true
      }
    ],
    "ReturnTypes": [
      {
        "Type": "personapi_dotnet.Models.Entities.Telefono",
        "MediaTypes": [
          "text/plain",
          "application/json",
          "text/json"
        ],
        "StatusCode": 200
      }
    ]
  },
  {
    "ContainingType": "personapi_dotnet.Controllers.TelefonosController",
    "Method": "Update",
    "RelativePath": "api/Telefonos/{numero}",
    "HttpMethod": "PUT",
    "IsController": true,
    "Order": 0,
    "Parameters": [
      {
        "Name": "numero",
        "Type": "System.String",
        "IsRequired": true
      },
      {
        "Name": "telefono",
        "Type": "personapi_dotnet.Models.Entities.Telefono",
        "IsRequired": true
      }
    ],
    "ReturnTypes": []
  },
  {
    "ContainingType": "personapi_dotnet.Controllers.TelefonosController",
    "Method": "Delete",
    "RelativePath": "api/Telefonos/{numero}",
    "HttpMethod": "DELETE",
    "IsController": true,
    "Order": 0,
    "Parameters": [
      {
        "Name": "numero",
        "Type": "System.String",
        "IsRequired": true
      }
    ],
    "ReturnTypes": []
  },
  {
    "ContainingType": "personapi_dotnet.Controllers.TelefonosController",
    "Method": "GetByPersona",
    "RelativePath": "api/Telefonos/persona/{duenio}",
    "HttpMethod": "GET",
    "IsController": true,
    "Order": 0,
    "Parameters": [
      {
        "Name": "duenio",
        "Type": "System.Int32",
        "IsRequired": true
      }
    ],
    "ReturnTypes": [
      {
        "Type": "System.Collections.Generic.IEnumerable\u00601[[personapi_dotnet.Models.Entities.Telefono, personapi-dotnet, Version=1.0.0.0, Culture=neutral, PublicKeyToken=null]]",
        "MediaTypes": [
          "text/plain",
          "application/json",
          "text/json"
        ],
        "StatusCode": 200
      }
    ]
  }
]